pargraph/__init__.py
pargraph/about.py
pargraph/engine/__init__.py
pargraph/engine/engine.py
pargraph/graph/__init__.py
pargraph/graph/annotation.py
pargraph/graph/decorators.py
pargraph/graph/objects.py
pargraph/utility/__init__.py
pargraph/utility/graphlib_graphblas.py
pargraph-0.9.6.dist-info/LICENSE
pargraph-0.9.6.dist-info/METADATA
pargraph-0.9.6.dist-info/WHEEL
pargraph-0.9.6.dist-info/top_level.txt
pargraph-0.9.6.dist-info/RECORD
