Metadata-Version: 2.1
Name: pargraph
Version: 0.9.6
Summary: Distributed graph computation library
Author-email: Citi <opensource@citi.com>
License: Apache 2.0
Project-URL: Home, https://github.com/Citi/pargraph
Classifier: Programming Language :: Python :: 3
Classifier: License :: OSI Approved :: Apache Software License
Classifier: Intended Audience :: Developers
Classifier: Operating System :: OS Independent
Classifier: Topic :: System :: Distributed Computing
Requires-Python: >=3.8
License-File: LICENSE
Requires-Dist: bidict
Requires-Dist: jsonschema
Requires-Dist: loky
Requires-Dist: cloudpickle
Requires-Dist: msgpack
Requires-Dist: pydot
Requires-Dist: typing-extensions ; python_version < "3.9"
Requires-Dist: graphlib-backport ; python_version < "3.9"
Provides-Extra: graphblas
Requires-Dist: python-graphblas ; extra == 'graphblas'
Requires-Dist: numpy ; extra == 'graphblas'
